ezfetch/__init__.py
ezfetch/colors.py
ezfetch/info.py
ezfetch/logo.py
ezfetch/main.py
ezfetch-1.0.5.dist-info/licenses/LICENSE
ezfetch-1.0.5.dist-info/METADATA
ezfetch-1.0.5.dist-info/WHEEL
ezfetch-1.0.5.dist-info/entry_points.txt
ezfetch-1.0.5.dist-info/top_level.txt
ezfetch-1.0.5.dist-info/RECORD
