Metadata-Version: 2.4
Name: ezfetch
Version: 1.0.5
Summary: A fast, cross-platform terminal system info tool written in Python (like neofetch)
Author: yokaimsi
Author-email: yokaimsi <contact.now.itachi@gmail.com>
License: MIT
Project-URL: Repository, https://github.com/yokaimsi/ezfetch
Keywords: neofetch,system-info,cli,terminal,fetch
Requires-Python: >=3.6
License-File: LICENSE
Requires-Dist: psutil
Dynamic: author
Dynamic: license-file
